21cmsense-2.2.1.dist-info/licenses/LICENSE.rst
py21cmsense/__init__.py
py21cmsense/_utils.py
py21cmsense/antpos.py
py21cmsense/baseline_filters.py
py21cmsense/beam.py
py21cmsense/cli.py
py21cmsense/config.py
py21cmsense/conversions.py
py21cmsense/observation.py
py21cmsense/observatory.py
py21cmsense/sensitivity.py
py21cmsense/theory.py
py21cmsense/units.py
py21cmsense/yaml.py
py21cmsense/data/__init__.py
py21cmsense/data/hera331drift_mod_0.135.npz
py21cmsense/data/ps_no_halos_nf0.521457_z9.50_useTs0_zetaX-1.0e+00_200_400Mpc_v2
py21cmsense/data/antpos/hera-h1c-idr3.txt
py21cmsense/data/antpos/layout_ecef_SKA_central.txt
py21cmsense/data/antpos/layout_ecef_SKA_core.txt
py21cmsense/data/antpos/layout_enu_ska_central.txt
py21cmsense/data/antpos/layout_enu_ska_core.txt
py21cmsense/data/antpos/mwa_phase2_compact_antpos.txt
py21cmsense/data/eos16-bright/ps_no_halos_z005.37_nf0.000000_useTs1_NX2.0e-01_alphaX1.5_TvirminX2.0e+05_aveTb000.24_Pop2_1024_1600Mpc_v3
py21cmsense/data/eos16-bright/ps_no_halos_z005.50_nf0.000000_useTs1_NX2.0e-01_alphaX1.5_TvirminX2.0e+05_aveTb000.24_Pop2_1024_1600Mpc_v3
py21cmsense/data/eos16-bright/ps_no_halos_z005.63_nf0.000000_useTs1_NX2.0e-01_alphaX1.5_TvirminX2.0e+05_aveTb000.24_Pop2_1024_1600Mpc_v3
py21cmsense/data/eos16-bright/ps_no_halos_z005.76_nf0.000000_useTs1_NX2.0e-01_alphaX1.5_TvirminX2.0e+05_aveTb000.24_Pop2_1024_1600Mpc_v3
py21cmsense/data/eos16-bright/ps_no_halos_z005.89_nf0.000000_useTs1_NX2.0e-01_alphaX1.5_TvirminX2.0e+05_aveTb000.24_Pop2_1024_1600Mpc_v3
py21cmsense/data/eos16-bright/ps_no_halos_z006.03_nf0.000000_useTs1_NX2.0e-01_alphaX1.5_TvirminX2.0e+05_aveTb000.23_Pop2_1024_1600Mpc_v3
py21cmsense/data/eos16-bright/ps_no_halos_z006.17_nf0.000000_useTs1_NX2.0e-01_alphaX1.5_TvirminX2.0e+05_aveTb000.23_Pop2_1024_1600Mpc_v3
py21cmsense/data/eos16-bright/ps_no_halos_z006.31_nf0.000000_useTs1_NX2.0e-01_alphaX1.5_TvirminX2.0e+05_aveTb000.23_Pop2_1024_1600Mpc_v3
21cmsense-2.2.1.dist-info/METADATA
21cmsense-2.2.1.dist-info/WHEEL
21cmsense-2.2.1.dist-info/entry_points.txt
21cmsense-2.2.1.dist-info/top_level.txt
21cmsense-2.2.1.dist-info/RECORD
