Metadata-Version: 2.4
Name: 21cmSense
Version: 2.2.1
Summary: Compute sensitivies of radio interferometers to the cosmic 21cm signal.
Author-email: Jonathan Pober <jonathon_pober@brown.edu>, Steven Murray <murray.steveng@gmail.com>, Matt Kolopanis <matthew.kolopanis@gmail.com>
Classifier: Development Status :: 5 - Production/Stable
Classifier: Intended Audience :: Science/Research
Classifier: License :: OSI Approved :: MIT License
Classifier: Operating System :: POSIX
Classifier: Operating System :: Unix
Classifier: Programming Language :: Python
Classifier: Programming Language :: Python :: 3
Classifier: Programming Language :: Python :: 3 :: Only
Classifier: Programming Language :: Python :: Implementation :: CPython
Requires-Python: >=3.9
License-File: LICENSE.rst
Requires-Dist: numpy>2
Requires-Dist: scipy
Requires-Dist: future
Requires-Dist: click
Requires-Dist: tqdm
Requires-Dist: pyyaml
Requires-Dist: astropy>=5
Requires-Dist: methodtools
Requires-Dist: pyuvdata>=3.0.0
Requires-Dist: cached_property
Requires-Dist: rich
Requires-Dist: attrs
Requires-Dist: hickleable>=0.1.1
Requires-Dist: lunarsky>=0.2.5
Provides-Extra: docs
Requires-Dist: sphinx>=1.3; extra == "docs"
Requires-Dist: sphinx-rtd-theme; extra == "docs"
Requires-Dist: numpydoc; extra == "docs"
Requires-Dist: nbsphinx; extra == "docs"
Requires-Dist: ipython; extra == "docs"
Provides-Extra: test
Requires-Dist: pre-commit; extra == "test"
Requires-Dist: pytest; extra == "test"
Requires-Dist: matplotlib; extra == "test"
Requires-Dist: pytest-cov; extra == "test"
Requires-Dist: pytest-xdist; extra == "test"
Provides-Extra: dev
Requires-Dist: 21cmSense[docs,test]; extra == "dev"
Requires-Dist: pre-commit; extra == "dev"
Requires-Dist: commitizen; extra == "dev"
Requires-Dist: ruff; extra == "dev"
Dynamic: license-file
